{
  "State": {
    "File": "newTest.csv"
  },
  "Cases": [
    {
      "Command": {
        "Cmd": "Setup"
      }
    },
    {
      "Command": {
        "Cmd": "Start"
      }
    },
    {
      "Command": {
        "Cmd": "ObjectsToCSV",
        "RecordObjects": [["SQL","Blue","Medium"],["Robotics","Yellow","Small"],["Compilers", "\"White-Orange-Black\"", "Thick"]]
      },
      "Response": {
        "Cmd": "ObjectsToCSV",
        "Records": "SQL,Blue,Medium\nRobotics,Yellow,Small\nCompilers,\"White-Orange-Black\",Thick"
      }
    },
    {
      "Command": {
        "Cmd": "CSVToObjects",
        "Records": "SQL,Blue,Medium\nRobotics,Yellow,Small\n\"Compilers\", \"White-Orange-Black\", \"Thick\""
      },
      "Response": {
        "Cmd": "CSVToObjects",
        "RecordObjects": [["SQL","Blue","Medium"],["Robotics","Yellow","Small"],["\"Compilers\"", " \"White-Orange-Black\"", " \"Thick"]]
      }
    },
    {
      "Command": {
        "Cmd": "WriteFile",
        "RecordObjects": [["SQL","Blue","Medium"],["Robotics","Yellow","Small"],["Compilers", "\"White-Orange-Black\"", "Thick"]]
      }
    },
    {
      "Command": {
        "Cmd": "ReadRecords"
      },
      "Response": {
        "Cmd": "ReadRecords",
        "RecordObjects": [["SQL","Blue","Medium"],["Robotics","Yellow","Small"],["Compilers", "White-Orange-Black", "Thick"]]
      }
    },
    {
      "Command": {
        "Cmd": "DeleteRecord",
        "Record": ["Compilers", "White-Orange-Black", "Thick"]
      },
      "Response": {
        "Cmd": "DeleteRecord",
        "RecordDeleted": true
      }
    },
    {
      "Command": {
        "Cmd": "AppendRecords",
        "RecordObjects": [["SQL","Blue","Medium"],["Robotics","Yellow","Small"],["Compilers", "White-Orange-Black", "Thick"]]
      }
    }
  ]
}